<?xml version="1.0" encoding="utf-8"?><toc><breadcrumbs><li><a href="09762912-d692-a3d7-9321-6b1a96b536ab.htm">Docs</a></li><li><a href="09762912-d692-a3d7-9321-6b1a96b536ab.htm">Namespaces</a></li><li><a href="27856e2b-abd7-b4b8-2d7c-eb73d5330f15.htm">PCBI.<wbr />Automation</a></li><li><a href="405422c3-30f1-eda3-8e77-dd1564afb400.htm">IPin</a></li></breadcrumbs><tocItems><li><a id="ebe56440-22a5-3138-4369-187dc1adff34" class="has-submenu" href="ebe56440-22a5-3138-4369-187dc1adff34.htm"><span data-tocFile="../toc/IDA0HC00MB0A.xml" class="icon toggle" onclick="ToggleExpandCollapse(this); return false;"><i class="fa fa-angle-right"> </i></span>Properties</a><ul class="toc-menu is-hidden"> </ul></li><li><a id="25c74f20-eec0-fcdb-8e52-df218242723a" class="has-submenu" href="25c74f20-eec0-fcdb-8e52-df218242723a.htm"><span data-tocFile="../toc/IDB0HC00MB0A.xml" class="icon toggle" onclick="ToggleExpandCollapse(this); return false;"><i class="fa fa-angle-right"> </i></span>Methods</a><ul class="toc-menu is-hidden"> </ul></li><li><a id="49b06f85-8c9f-ee46-20d5-e739ff1915e0" class="has-submenu" href="49b06f85-8c9f-ee46-20d5-e739ff1915e0.htm"><span data-tocFile="../toc/IDC0HC00MB0A.xml" class="icon toggle" onclick="ToggleExpandCollapse(this); return false;"><i class="fa fa-angle-right"> </i></span>Operators</a><ul class="toc-menu is-hidden"> </ul></li></tocItems></toc>