<?xml version="1.0" encoding="utf-8"?><toc><breadcrumbs><li><a href="09762912-d692-a3d7-9321-6b1a96b536ab.htm">Docs</a></li><li><a href="09762912-d692-a3d7-9321-6b1a96b536ab.htm">Namespaces</a></li><li><a href="482ef245-0f53-e4ff-6bb8-88889f149e67.htm">PCBI_<wbr />Net<wbr />Groups.<wbr />Report</a></li></breadcrumbs><tocItems><li><a id="d3c79c19-8dd5-054f-caf7-420a22a9043b" class="has-submenu" href="d3c79c19-8dd5-054f-caf7-420a22a9043b.htm"><span data-tocFile="../toc/IDA0NF0A.xml" class="icon toggle" onclick="ToggleExpandCollapse(this); return false;"><i class="fa fa-angle-right"> </i></span>Net<wbr />Group<wbr />Distances<wbr />HTMLReport</a><ul class="toc-menu is-hidden"> </ul></li></tocItems></toc>