<?xml version="1.0" encoding="utf-8"?><toc><breadcrumbs><li><a href="09762912-d692-a3d7-9321-6b1a96b536ab.htm">Docs</a></li><li><a href="09762912-d692-a3d7-9321-6b1a96b536ab.htm">Namespaces</a></li><li><a href="96aec3a0-ad34-d518-1622-e6938b767d14.htm">PCBI_<wbr />DFM_<wbr />Analysis</a></li></breadcrumbs><tocItems><li><a id="3d3cbcd2-b9bb-1116-2fbe-20718aff33d6" href="3d3cbcd2-b9bb-1116-2fbe-20718aff33d6.htm">DFMAnalysis<wbr />Type</a></li><li><a id="07de0f8b-7a0f-4744-da99-850a2b24952c" class="has-submenu" href="07de0f8b-7a0f-4744-da99-850a2b24952c.htm"><span data-tocFile="../toc/IDB0SD0A.xml" class="icon toggle" onclick="ToggleExpandCollapse(this); return false;"><i class="fa fa-angle-right"> </i></span>DFMData<wbr />Provider</a><ul class="toc-menu is-hidden"> </ul></li><li><a id="99b8e965-3738-b13e-e495-5f9fa516ad05" class="has-submenu" href="99b8e965-3738-b13e-e495-5f9fa516ad05.htm"><span data-tocFile="../toc/IDC0SD0A.xml" class="icon toggle" onclick="ToggleExpandCollapse(this); return false;"><i class="fa fa-angle-right"> </i></span>DFMData<wbr />Provider.<wbr />CMPObject</a><ul class="toc-menu is-hidden"> </ul></li><li><a id="87993751-0557-93aa-edda-c726153e91d2" class="has-submenu" href="87993751-0557-93aa-edda-c726153e91d2.htm"><span data-tocFile="../toc/IDD0SD0A.xml" class="icon toggle" onclick="ToggleExpandCollapse(this); return false;"><i class="fa fa-angle-right"> </i></span>DFMData<wbr />Provider.<wbr />DFMObject</a><ul class="toc-menu is-hidden"> </ul></li><li><a id="65dd6c0a-dd95-e8e1-b0ce-437d3d68c04e" class="has-submenu" href="65dd6c0a-dd95-e8e1-b0ce-437d3d68c04e.htm"><span data-tocFile="../toc/IDE0SD0A.xml" class="icon toggle" onclick="ToggleExpandCollapse(this); return false;"><i class="fa fa-angle-right"> </i></span>DFMData<wbr />Provider.<wbr />ODBObject</a><ul class="toc-menu is-hidden"> </ul></li><li><a id="00ccde62-43df-72c4-bc2e-e7a1b79bc1d3" class="has-submenu" href="00ccde62-43df-72c4-bc2e-e7a1b79bc1d3.htm"><span data-tocFile="../toc/IDF0SD0A.xml" class="icon toggle" onclick="ToggleExpandCollapse(this); return false;"><i class="fa fa-angle-right"> </i></span>DFMImage<wbr />Service</a><ul class="toc-menu is-hidden"> </ul></li><li><a id="2cda7825-4f6a-1063-5d39-a2318f95bbc1" class="has-submenu" href="2cda7825-4f6a-1063-5d39-a2318f95bbc1.htm"><span data-tocFile="../toc/IDG0SD0A.xml" class="icon toggle" onclick="ToggleExpandCollapse(this); return false;"><i class="fa fa-angle-right"> </i></span>PCBIDFMAnalysis</a><ul class="toc-menu is-hidden"> </ul></li><li><a id="bd4c1200-bc74-153a-bac3-6ecbcd073623" href="bd4c1200-bc74-153a-bac3-6ecbcd073623.htm">PCBIDFMAnalysis.<wbr />DFMReport<wbr />Key</a></li></tocItems></toc>