<?xml version="1.0" encoding="utf-8"?><toc><breadcrumbs><li><a href="09762912-d692-a3d7-9321-6b1a96b536ab.htm">Docs</a></li><li><a href="09762912-d692-a3d7-9321-6b1a96b536ab.htm">Namespaces</a></li><li><a href="5a88cd13-e90b-5cd8-cef0-8ff9bba17586.htm">PCBI_<wbr />Creepage<wbr />Distances</a></li><li><a href="41404239-bdfd-22ee-8052-46a74c54edb7.htm">Creepage<wbr />Html<wbr />Report</a></li></breadcrumbs><tocItems><li><a id="60a971d3-07d9-13ac-d9cf-156bda842cb3" href="60a971d3-07d9-13ac-d9cf-156bda842cb3.htm">Constructor</a></li><li><a id="73424fc8-8219-09cc-5100-046e0b2357c7" class="has-submenu" href="73424fc8-8219-09cc-5100-046e0b2357c7.htm"><span data-tocFile="../toc/IDBA0QD0A.xml" class="icon toggle" onclick="ToggleExpandCollapse(this); return false;"><i class="fa fa-angle-right"> </i></span>Properties</a><ul class="toc-menu is-hidden"> </ul></li><li><a id="182d3121-9cfd-823e-4a62-001e6c3eec81" class="has-submenu" href="182d3121-9cfd-823e-4a62-001e6c3eec81.htm"><span data-tocFile="../toc/IDCA0QD0A.xml" class="icon toggle" onclick="ToggleExpandCollapse(this); return false;"><i class="fa fa-angle-right"> </i></span>Methods</a><ul class="toc-menu is-hidden"> </ul></li></tocItems></toc>