<?xml version="1.0" encoding="utf-8"?><toc><breadcrumbs><li><a href="09762912-d692-a3d7-9321-6b1a96b536ab.htm">Docs</a></li><li><a href="09762912-d692-a3d7-9321-6b1a96b536ab.htm">Namespaces</a></li><li><a href="7d65621c-9961-e4c9-7345-d19457a82164.htm">PCBI_<wbr />API_<wbr />Extensions.<wbr />Controls.<wbr />Renderers</a></li><li><a href="4d176bed-a9e4-1394-5f27-8d9dc6fbc496.htm">Toggle<wbr />Switch<wbr />Android<wbr />Renderer</a></li></breadcrumbs><tocItems><li><a id="aa00df75-395b-2473-dc28-4f64a44ef0e3" href="aa00df75-395b-2473-dc28-4f64a44ef0e3.htm">Constructor</a></li><li><a id="125d29b3-30f1-a254-3359-e7d0c4e130db" class="has-submenu" href="125d29b3-30f1-a254-3359-e7d0c4e130db.htm"><span data-tocFile="../toc/IDBA0HC0A.xml" class="icon toggle" onclick="ToggleExpandCollapse(this); return false;"><i class="fa fa-angle-right"> </i></span>Properties</a><ul class="toc-menu is-hidden"> </ul></li><li><a id="03bb60af-906c-ae6b-edeb-5abb15f9e10a" class="has-submenu" href="03bb60af-906c-ae6b-edeb-5abb15f9e10a.htm"><span data-tocFile="../toc/IDCA0HC0A.xml" class="icon toggle" onclick="ToggleExpandCollapse(this); return false;"><i class="fa fa-angle-right"> </i></span>Methods</a><ul class="toc-menu is-hidden"> </ul></li></tocItems></toc>