<?xml version="1.0" encoding="utf-8"?><toc><breadcrumbs><li><a href="09762912-d692-a3d7-9321-6b1a96b536ab.htm">Docs</a></li><li><a href="09762912-d692-a3d7-9321-6b1a96b536ab.htm">Namespaces</a></li><li><a href="7d65621c-9961-e4c9-7345-d19457a82164.htm">PCBI_<wbr />API_<wbr />Extensions.<wbr />Controls.<wbr />Renderers</a></li><li><a href="15161905-2ca6-6f10-3f4a-5a5100e6d21c.htm">Toggle<wbr />Switch<wbr />IOS<wbr />5Renderer</a></li></breadcrumbs><tocItems><li><a id="ba48ed62-27f2-0842-2b17-e9cab830a748" href="ba48ed62-27f2-0842-2b17-e9cab830a748.htm">Constructor</a></li><li><a id="c855aa2e-ff7f-ee86-90f8-61153f7d5c12" class="has-submenu" href="c855aa2e-ff7f-ee86-90f8-61153f7d5c12.htm"><span data-tocFile="../toc/IDBE0HC0A.xml" class="icon toggle" onclick="ToggleExpandCollapse(this); return false;"><i class="fa fa-angle-right"> </i></span>Properties</a><ul class="toc-menu is-hidden"> </ul></li><li><a id="f40dd4ed-1877-acb4-0465-c81f330eb758" class="has-submenu" href="f40dd4ed-1877-acb4-0465-c81f330eb758.htm"><span data-tocFile="../toc/IDCE0HC0A.xml" class="icon toggle" onclick="ToggleExpandCollapse(this); return false;"><i class="fa fa-angle-right"> </i></span>Methods</a><ul class="toc-menu is-hidden"> </ul></li></tocItems></toc>