<?xml version="1.0" encoding="utf-8"?><toc><breadcrumbs><li><a href="09762912-d692-a3d7-9321-6b1a96b536ab.htm">Docs</a></li><li><a href="09762912-d692-a3d7-9321-6b1a96b536ab.htm">Namespaces</a></li><li><a href="e2bb2fe6-ff13-0d10-1e3e-5c6d662d9bec.htm">PCBI_<wbr />Stencil_<wbr />Editor.<wbr />Stencil<wbr />Creation<wbr />Rules</a></li><li><a href="cc2df2ce-c931-6463-f05c-146d1cbe369c.htm">Stencil<wbr />Script<wbr />Free<wbr />Symbol</a></li></breadcrumbs><tocItems><li><a id="b3d68d47-55fc-546d-85be-f05dbf932584" href="b3d68d47-55fc-546d-85be-f05dbf932584.htm">Constructor</a></li><li><a id="707eafb4-c5d2-75f5-d4c9-f44634d8fdc6" class="has-submenu" href="707eafb4-c5d2-75f5-d4c9-f44634d8fdc6.htm"><span data-tocFile="../toc/IDBF03G0A.xml" class="icon toggle" onclick="ToggleExpandCollapse(this); return false;"><i class="fa fa-angle-right"> </i></span>Properties</a><ul class="toc-menu is-hidden"> </ul></li><li><a id="e247b162-e1f1-6e45-dffd-eb2e029d87a9" class="has-submenu" href="e247b162-e1f1-6e45-dffd-eb2e029d87a9.htm"><span data-tocFile="../toc/IDCF03G0A.xml" class="icon toggle" onclick="ToggleExpandCollapse(this); return false;"><i class="fa fa-angle-right"> </i></span>Methods</a><ul class="toc-menu is-hidden"> </ul></li><li><a id="1ac2514c-05b7-82eb-b765-32b6378872f3" class="has-submenu" href="1ac2514c-05b7-82eb-b765-32b6378872f3.htm"><span data-tocFile="../toc/IDDF03G0A.xml" class="icon toggle" onclick="ToggleExpandCollapse(this); return false;"><i class="fa fa-angle-right"> </i></span>Fields</a><ul class="toc-menu is-hidden"> </ul></li></tocItems></toc>